hepevd-0.4.4.dist-info/RECORD
hepevd-0.4.4.dist-info/WHEEL
hepevd-0.4.4.dist-info/METADATA
hepevd-0.4.4.dist-info/licenses/LICENSE
HepEVD/_hepevd_impl.abi3.so
HepEVD/__init__.pyi
HepEVD/__init__.py
HepEVD/py.typed
HepEVD/web/constants.js
HepEVD/web/data_loader.js
HepEVD/web/ui.js
HepEVD/web/hep_evd.js
HepEVD/web/index.html
HepEVD/web/colourmaps.js
HepEVD/web/mc_data_state.js
HepEVD/web/hit_type_state.js
HepEVD/web/__init__.py
HepEVD/web/rendering.js
HepEVD/web/particle_data_state.js
HepEVD/web/states.js
HepEVD/web/render_state.js
HepEVD/web/hits.js
HepEVD/web/hit_data_state.js
HepEVD/web/interactions.js
HepEVD/web/marker_data_state.js
HepEVD/web/helpers.js
HepEVD/web/hep_evd.css
HepEVD/web/camera_and_controls.js
HepEVD/web/particle_menu.js
HepEVD/web/markers.js
HepEVD/web/vendor/theme-change.js
HepEVD/web/vendor/katex.js
HepEVD/web/vendor/daisyui.css
HepEVD/web/vendor/es-module-shims.js
HepEVD/web/vendor/tailwindcss.js
