Metadata-Version: 2.4
Name: hepevd
Version: 0.4.4
Summary: Event Display for Particle Physics Data
Author-Email: Ryan Cross <ryan.cross@warwick.ac.uk>
License-Expression: MIT
Project-URL: homepage, https://github.com/CrossR/HepEVD
Requires-Python: >=3.8
